vishwa_excel_formulas/__Init__.py
vishwa_excel_formulas/arith_formulas.py
vishwa_excel_formulas/excel_arith_fomulas.py
vishwa_excel_formulas-1.1.0.dist-info/LICENSE
vishwa_excel_formulas-1.1.0.dist-info/METADATA
vishwa_excel_formulas-1.1.0.dist-info/WHEEL
vishwa_excel_formulas-1.1.0.dist-info/top_level.txt
vishwa_excel_formulas-1.1.0.dist-info/RECORD
