Metadata-Version: 2.1
Name: vishwa_excel_formulas
Version: 1.1.0
Summary: Excel Basic Forumla Package
Author: Vishwa
Author-email: vishwa.automationhub@gmail.com
Classifier: Programming Language :: Python :: 3
Classifier: License :: OSI Approved :: MIT License
Classifier: Operating System :: OS Independent
Requires-Python: >=3.0
License-File: LICENSE
